quala/__init__.py
quala/__init__.pyi
quala/_quala.pyd
quala/_quala.pyi
quala/py.typed
quala-0.0.1a1.dist-info/LICENSE
quala-0.0.1a1.dist-info/METADATA
quala-0.0.1a1.dist-info/WHEEL
quala-0.0.1a1.dist-info/entry_points.txt
quala-0.0.1a1.dist-info/RECORD
