Metadata-Version: 2.1
Name: quala
Version: 0.0.1a1
Summary: Quasi-Newton algorithms and other accelerators
Keywords: optimization
Author-email: Pieter P <pieter.p.dev@outlook.com>
Requires-Python: >=3.7
Classifier: Development Status :: 3 - Alpha
Classifier: Intended Audience :: Science/Research
Classifier: Topic :: Scientific/Engineering
Classifier: License :: OSI Approved :: GNU Lesser General Public License v3 (LGPLv3)
Classifier: Programming Language :: Python :: 3
Classifier: Programming Language :: Python :: 3.8
Classifier: Programming Language :: Python :: 3.9
Classifier: Programming Language :: Python :: 3.10
Classifier: Operating System :: POSIX :: Linux
Classifier: Operating System :: Microsoft :: Windows
Requires-Dist: numpy
Requires-Dist: sphinx~=5.1 ; extra == "docs"
Requires-Dist: matplotlib ; extra == "docs"
Requires-Dist: breathe ; extra == "docs"
Requires-Dist: furo ; extra == "docs"
Project-URL: Bug Tracker, https://github.com/tttapa/quala/issues
Project-URL: Documentation, https://tttapa.github.io/quala
Project-URL: Source, https://github.com/tttapa/quala
Provides-Extra: docs
